{"id":"123eefc46a5797eae4fabd09","title":"OPERATIONS.md","source_path":"programs/skinharmony-core/OPERATIONS.md","text":"# Operazioni SkinHarmony Translation Hub\n\n## Installazione\n\n- Caricare zip `dist/skinharmony-translation-hub-latest.zip`.\n- Attivare plugin WordPress.\n- Verificare namespace `sh-core/v1`.\n\n## Aggiornamento\n\n- Bump versione nel plugin.\n- PHP lint file modificati.\n- Test `node scripts/check_skinharmony_core_plugin.mjs`.\n- Test legacy esteso `node scripts/test_skinharmony_core_plugin.js`.\n- Creare zip.\n- Caricare e testare endpoint live.\n\n## Test Minimi\n\n- Route `site/content-governance`.\n- Test copy freddo/astratto.\n- Test claim rischioso.\n- Report in `reports/core-translator`.\n- Dopo ogni modifica eseguire Program Registry:\n  - `npm run codex:program-registry -- --file <file-core> --file SHARED_MEMORY/programs/skinharmony-core/<mappa-aggiornata>.md`\n\n## Lettura A Blocchi\n\n1. `BLOCK_01_BOOTSTRAP_ACCESS_STORAGE_MAP.md` - bootstrap plugin, settings, storage, automation key, Core Admin.\n2. `BLOCK_02_TRANSLATION_CONTENT_GOVERNANCE_MAP.md` - traduzione pagina/strutturata, language runtime, multiverse, content governance e orchestrator.\n3. `BLOCK_03_QUEUE_REVIEW_PROVIDER_INTEGRITY_SEO_MAP.md` - queue, review, provider, integrity e SEO bridge.\n4. `BLOCK_04_CONTROL_PLANE_NETWORK_LICENSE_ACCESS_MAP.md` - snapshot decisionale, network connector, Smart Desk bridge, licenza e ruoli.\n5. `BLOCK_05_MEMORY_GLOSSARY_RUNTIME_DELTA_SOFTWARE_MAP.md` - policy pack, memory, runtime layer, delta, autosync e cataloghi software.\n6. `BLOCK_06_LANGUAGE_CORE_ASSETS_CONTRACTS_POLICY_MAP.md` - contratti, dizionari, policy pack, termini, claim rules e WaaS.\n\n## Regole Traduzione / Content Governance\n\n- Non modificare automaticamente la lingua sorgente.\n- Non tradurre HTML finale se è disponibile payload strutturato.\n- Se manca memory approvata in `memory_only`, restituire errore/review, non inventare.\n- Content Governance deve proporre correzioni puntuali, non bloccare tutto per una parola.\n- Testi marketing devono spiegare problema, funzionamento, valore, limite e CTA.\n- Claim medici/terapeutici richiedono riscrittura e review.\n- Se Universal Core remoto non è raggiungibile e la policy lo richiede, `publish_safe` deve essere falso o richiedere review.\n- Queue, provider e SEO bridge non devono pubblicare contenuti sensibili saltando review e claim guard.\n- Integrity readiness deve distinguere tradotto, approvato e pubblicabile.\n- Smart Desk bridge indica raggiungibilita, non sync completo dei dati.\n- Network sync deve usare API key scoped e non deve mescolare tenant/brand.\n- Universal Core remoto, quando configurato, resta giudice primario rispetto alla decisione locale.\n- Ogni modulo che produce testo deve usare `domain` e `key_path` stabili.\n- Autosync crea job controllabili, non pubblicazione automatica.\n- Cataloghi software/UI devono usare Software Bridge invece di traduzioni sparse.\n- Le parole interne tecniche non devono finire nel sito pubblico se non sono nomi prodotto protetti.\n- Policy pack e contratti sono parte del prodotto: aggiornarli richiede registry e report.\n\n## Fallback\n\n- Ripristinare zip precedente.\n- Usare backup pagina prima di batch replace.\n- Non eliminare automation key attive senza report.\n","redactions":0}
