{"id":"14894b9f4313cb0199172acf","title":"SUITE_5_3_45_REJECTED_ROLLBACK_TO_5_3_44_2026-06-06.md","source_path":"handoffs/SUITE_5_3_45_REJECTED_ROLLBACK_TO_5_3_44_2026-06-06.md","text":"# Suite 5.3.45 Rejected -> Rollback to 5.3.44\n\nData: `2026-06-06`\n\n## Decisione\n- `5.3.45` non va bene come baseline operativa.\n- Si riparte da `5.3.44`.\n\n## Motivo\n- La `light view` sul `CRM B2B` non e allineata al flusso operativo richiesto.\n- Aprire il CRM e vedere una schermata intermedia `vista leggera` e stato giudicato sbagliato.\n\n## Regola corretta\n- I moduli operativi come `CRM B2B` devono aprire direttamente nella vista completa.\n- La cache/snapshot deve stare dietro le quinte:\n  - velocizzare il caricamento;\n  - evitare builder profondi inutili;\n  - non cambiare il comportamento percepito da chi lavora.\n\n## Baseline corrente\n- Versione di riferimento: `5.3.44`\n- Artefatto locale: `dist/skinharmony-site-suite-5.3.44.zip`\n- Closure locale: `reports/wordpress/SUITE_OPERATIONAL_CLOSURE_5_3_44_LOCAL_2026-05-19.json`\n\n## Nota per il prossimo ciclo\n- Non riproporre `light view` come gateway UX per il CRM.\n- Se si riapre il lavoro performance:\n  - partire da `5.3.44`;\n  - mantenere apertura diretta dei moduli operativi;\n  - usare cache locale, snapshot e refresh parziale solo come meccanica interna.\n","redactions":0}
