{"id":"534cb9224e9b1af83de3cffd","title":"UNIVERSAL_CORE_RENDER_SOFTWARE_LANGUAGE_GATE_2026-06-01.md","source_path":"reports/core-translator/UNIVERSAL_CORE_RENDER_SOFTWARE_LANGUAGE_GATE_2026-06-01.md","text":"# Universal Core Render Software Language Gate\n\nData: 2026-06-01\n\n## Esito\nIl gate lingua software orizzontale e ora attivo anche su Render dentro Universal Core Service.\n\nNon e piu solo locale: Smart Desk, AI Gold, Site Suite, SkinHarmony Core/traduttore e futuri moduli possono chiamare un passaggio server comune.\n\n## Deploy\n- servizio Render: `skinharmony-universal-core`\n- service id: `srv-d82c9j3tqb8s73cgriag`\n- deploy id: `dep-d8euhqpkh4rs73eme0h0`\n- commit: `51128414081410fddcd5a8ace976d4290794f812`\n- versione live verificata: `0.3.17-software-language-gate`\n\n## Rotte\n- `GET /v1/software-language-gate/schema`\n- `POST /v1/software-language-gate/evaluate`\n- alias API: `/api/v1/software-language-gate/schema`\n- alias API: `/api/v1/software-language-gate/evaluate`\n\n## Regola obbligatoria\nLa rotta e un gate, non un report decorativo.\n\nSe la risposta contiene:\n- `language_ready=false`\n- `decision=blocked`\n- `action_mediation.execution_allowed=false`\n\nallora lingua/UI/copy AI non sono pronti per demo, release o vendita.\n\n## Pipeline\n- `V2`: filtro semantico anti-rumore, rimuove dizionari, repair map, regex e frammenti codice.\n- `V1`: filtro policy di scrittura, rimuove copy generico a basso segnale.\n- `V0`: gate finale, tiene residui visibili o high-risk.\n\n## Verifica live\nHealth live:\n- `ok=true`\n- `service=skinharmony-universal-core-service`\n- `version=0.3.17-software-language-gate`\n- `mode=production`\n\nSchema live:\n- `mandatory=true`\n- `horizontal=true`\n- `applies_to=[skinharmony_core_translator, smartdesk, ai_gold, site_suite, future_core_nyra_software]`\n- `required_pipeline=[v2_semantic_filter, v1_writing_policy_filter, v0_final_visible_risk_gate]`\n\nEvaluate live autenticato:\n- `language_ready=false`\n- `decision=blocked`\n- `execution_allowed=false`\n- `entries=4`\n- `raw_findings_before_noise=3`\n- `noise_removed=1`\n- `findings=2`\n- `blocking_high=2`\n\n## Test locali\n`npm --prefix services/universal-core-service test`\n\nEsito: OK. Il test include:\n- schema gate lingua;\n- evaluate lingua tedesca sporca;\n- blocco release con `language_ready=false`;\n- rimozione rumore V2 su repair rule;\n- manifest SDK con rotta `software_language_gate`.\n\n## Prossimo passo\nCollegare i client:\n- SkinHarmony Core/traduttore deve chiamare questo gate prima di salvare cataloghi ufficiali;\n- Smart Desk deve chiamarlo prima di dichiarare lingua pronta o usare copy AI Gold runtime;\n- Suite deve esporlo nelle verifiche release/translator;\n- i futuri moduli Core/Nyra devono usarlo come preflight obbligatorio.\n","redactions":0}
