{"id":"6fed5cad8c99d67f54b45389","title":"SEMANTIC_PREMIUM_VALIDATOR_MVP_2026-05-21.md","source_path":"reports/SEMANTIC_PREMIUM_VALIDATOR_MVP_2026-05-21.md","text":"# SEMANTIC_PREMIUM_VALIDATOR_MVP_2026-05-21\n\n## Obiettivo\n\nImplementare il primo `semantic premium language validator` per non fermarsi alla sola blocklist lessicale.\n\n## Implementazione chiusa\n\n### Connector\n\nAggiornato `packages/core-codex-connector/src/cli.mjs` con:\n\n- `SEMANTIC_PREMIUM_RULES`\n- conteggio ripetizioni concettuali\n- metrica base su:\n  - ritmo frasi\n  - astratto vs concreto\n- integrazione nel comando:\n  - `sh-core-codex client-facing-check --file PATH`\n\n### Suite\n\nAggiornato `wordpress/plugins/skinharmony-site-suite/skinharmony-site-suite.php` con:\n\n- `evaluate_suite_client_facing_language`\n- salvataggio di:\n  - `public_language_semantic_issues`\n  - `public_language_semantic_summary`\n- visualizzazione `Semantic issues` nel `Site Clone Engine`\n\n## Verifiche tecniche\n\n- `node --check packages/core-codex-connector/src/cli.mjs` -> OK\n- `/opt/homebrew/bin/php -l wordpress/plugins/skinharmony-site-suite/skinharmony-site-suite.php` -> `No syntax errors detected`\n\n## Esito pratico\n\n### O3 System\n\nLessico interno:\n\n- pulito\n- `client-facing lexical policy = clean`\n\nValidator semantico:\n\n- `rewrite_required`\n- motivo: `high_repetition_pressure`\n\nDettaglio rilevato:\n\n- `protocollo:12`\n- `posizionamento:4`\n- `ordinato:4`\n- `coerente:4`\n- `struttura:3`\n- `premium:5`\n\n### Termosauna\n\nLessico interno:\n\n- pulito\n- `client-facing lexical policy = clean`\n\nValidator semantico:\n\n- `rewrite_required`\n- motivo: `high_repetition_pressure`\n\nDettaglio rilevato:\n\n- `protocollo:5`\n- `posizionamento:4`\n- `coerente:4`\n- `struttura:3`\n- `percezione:4`\n- `premium:6`\n\n## Conclusione\n\nIl sistema e passato da:\n\n- `parole vietate`\n\na:\n\n- `parole vietate + difetti stilistici principali`\n\nQuindi il controllo ora riesce a dire una cosa piu utile:\n\n- il testo non e sporco di termini interni\n- ma suona ancora troppo AI per ripetizione concettuale\n\n## Prossimo passo giusto\n\nRafforzare il ramo `technology/device` con riscrittura anti-ripetizione:\n\n- meno reuse di `protocollo`\n- meno reuse di `premium`\n- meno reuse di `coerente / ordinato / posizionamento`\n- piu concretezza sensoriale\n- piu differenza tra:\n  - `institutional`\n  - `center_conversion`\n","redactions":0}
