{"id":"7b38e56dc0d6328ab8e4b4e7","title":"2026-05-29t09_00_16.697z_codex_02_connector_finalize_limited_evidence_codex_02_codex_02_1780045216696_intent.json","source_path":"supervision/2026-05-29t09_00_16.697z_codex_02_connector_finalize_limited_evidence_codex_02_codex_02_1780045216696_intent.json","text":"{\n  \"intent_id\": \"2026-05-29t09_00_16.697z_codex_02_connector_finalize_limited_evidence\",\n  \"generated_at\": \"2026-05-29T09:00:16.697Z\",\n  \"agent_id\": \"codex_02\",\n  \"session_id\": \"codex_02_1780045216696\",\n  \"trace_id\": \"trace_codex_02_codex_02_1780045216696_1780045216696\",\n  \"title\": \"Connector finalize limited evidence\",\n  \"request\": \"Aggiungere al Core Codex Connector una chiusura limitata documentata per lavori senza E2E completo applicabile, mantenendo vincolo prima/durante/dopo e prove sostitutive.\",\n  \"success_criteria\": \"Patch connettore testata, programma aggiornato, report condiviso salvato, cleanup e finalize verdi.\",\n  \"expected_depth\": \"normal\",\n  \"files\": [],\n  \"status\": \"active\",\n  \"rule\": \"Codex deve lavorare dentro task contract, aggiornare pulse e non chiudere senza cleanup/test/report.\"\n}","redactions":0}
