{"id":"7d9e0e495ed690e6c7597eb2","title":"SUITE_ELENA_VISUAL_REFRESH_1571_2026-05-21.md","source_path":"reports/SUITE_ELENA_VISUAL_REFRESH_1571_2026-05-21.md","text":"# SUITE ELENA VISUAL REFRESH 1571 - 2026-05-21\n\n## Obiettivo\nRiallineare la bozza Elena `1571` a una resa piu premium anche sul piano grafico, senza perdere il miglioramento gia ottenuto sul tono e sulla narrativa.\n\n## Diagnosi corretta\n- Il copy era salito di livello.\n- La grafica invece era arretrata: pagina troppo piatta, troppo “ordinata”, meno retail/editoriale.\n- Il collo di bottiglia non era WordPress ma il percorso governance: la nuova pagina usava CSS inline, quindi non poteva essere trattata come `commercial_page_factory`.\n\n## Correzione eseguita\n- Mantenuto il miglioramento del copy.\n- Ripristinata una shell piu forte e piu visuale:\n  - hero piu autorevole\n  - gallery band\n  - editorial band\n  - benefit band\n  - card formula/story piu leggibili\n  - FAQ piu corte\n  - finale con firma piu netta\n- Aggiunte frasi-firma piu memorabili e meno neutre.\n- Ridotto il tono “compliance elegante” a favore di:\n  - texture\n  - finish\n  - ritualita\n  - presenza sensoriale\n\n## Manifest e governance\n- Creato manifest corretto per update visivo produzione:\n  - `reports/wordpress/elena-page-1571-visual-refresh-manifest-2026-05-21.json`\n- Scelta corretta:\n  - `action_type = update`\n  - non `commercial_page_factory`\n  - per non forzare un contratto sbagliato su contenuto con CSS inline\n\n## Esito tecnico\n- Preflight governance: `allow`\n- Update WordPress: `HTTP 200`\n- Pagina aggiornata: `1571`\n- Modified: `2026-05-21T21:23:10`\n\n## File\n- Sorgente locale:\n  - `wordpress/elena-sartoria-nutriente-page.html`\n- Manifest:\n  - `reports/wordpress/elena-page-1571-visual-refresh-manifest-2026-05-21.json`\n- Report preflight:\n  - `reports/wordpress/wp_page_governance_preflight_latest.json`\n\n## Nota operativa\nRegola utile fissata: quando una pagina usa CSS inline o classi non page-factory, non va spinta con manifesto `commercial_page_factory`. Va usato un manifest di `update` coerente con il contenuto reale.\n","redactions":0}
