{"id":"862d0bd746861bbac2d8a138","title":"2026-05-29t15_25_10.523z_checklist_smoke_01_checklist_smoke_checklist_smoke_01_checklist_smoke_01_session_intent.json","source_path":"supervision/2026-05-29t15_25_10.523z_checklist_smoke_01_checklist_smoke_checklist_smoke_01_checklist_smoke_01_session_intent.json","text":"{\n  \"intent_id\": \"2026-05-29t15_25_10.523z_checklist_smoke_01_checklist_smoke\",\n  \"generated_at\": \"2026-05-29T15:25:10.523Z\",\n  \"agent_id\": \"checklist_smoke_01\",\n  \"session_id\": \"checklist_smoke_01_session\",\n  \"trace_id\": \"trace_checklist_smoke_01_checklist_smoke_01_session_1780068310521\",\n  \"title\": \"Checklist smoke\",\n  \"request\": \"Verificare enforcement checklist\",\n  \"success_criteria\": \"Finalize blocca con checklist aperta e passa quando chiusa\",\n  \"expected_depth\": \"normal\",\n  \"files\": [],\n  \"status\": \"active\",\n  \"rule\": \"Codex deve lavorare dentro task contract, aggiornare pulse e non chiudere senza cleanup/test/report.\"\n}","redactions":0}
