{"id":"ada89f5a013ca043852a1869","title":"2026-05-24t16_45_23.499z_cristiancardarello_pulse_cristiancardarello_cristiancardarello_1779641067526_pulse.json","source_path":"supervision/2026-05-24t16_45_23.499z_cristiancardarello_pulse_cristiancardarello_cristiancardarello_1779641067526_pulse.json","text":"{\n  \"pulse_id\": \"2026-05-24t16_45_23.499z_cristiancardarello_pulse\",\n  \"generated_at\": \"2026-05-24T16:45:23.499Z\",\n  \"agent_id\": \"cristiancardarello\",\n  \"session_id\": \"cristiancardarello_1779641067526\",\n  \"title\": \"Pulse Codex\",\n  \"summary\": \"Suite 5.2.34: preview collegata agli slot template authority; test inline 23/23, plugin 5.2.34 pass, governance/page-factory pass.\",\n  \"files\": [\n    \"SHARED_MEMORY/reports/SUITE_5_2_34_TEMPLATE_BUILDER_CONNECTED_PREVIEW_2026-05-24.md\"\n  ],\n  \"tests\": [],\n  \"next\": \"Eseguire closure package e verifica zip.\",\n  \"risk\": \"unknown\",\n  \"latest_core_report\": \"/Users/cristiancardarello/skinharmony-codex/reports/codex-core/codex_core_gate_latest.json\",\n  \"intent\": {\n    \"intent_id\": \"2026-05-24t16_45_23.004z_cristiancardarello_suite_template_builder_5.2.34_connec\",\n    \"title\": \"Suite Template Builder 5.2.34 connected preview\",\n    \"request\": \"Chiudere il difetto: preview Builder parziale e non completamente collegata agli slot template.\",\n    \"success_criteria\": \"Zip 5.2.34 generato, slot preview collegati e test passati.\"\n  },\n  \"core2_supervision\": {\n    \"verdict\": \"attention\",\n    \"flags\": [\n      \"rischio_non_classificato\"\n    ],\n    \"intent_overlap\": 0.308,\n    \"correction\": \"Aggiungere evidenze concrete: file, test, prossima azione e confronto con l'intento.\"\n  }\n}","redactions":0}
