{"id":"c81f2d0c59a4f36b27fd5575","title":"2026-06-05t08_19_46.568z_cristiancardarello_suite_5.3.36_fast_path_locale.json","source_path":"checkpoints/2026-06-05t08_19_46.568z_cristiancardarello_suite_5.3.36_fast_path_locale.json","text":"{\n  \"checkpoint_id\": \"2026-06-05t08_19_46.568z_cristiancardarello_suite_5.3.36_fast_path_locale\",\n  \"generated_at\": \"2026-06-05T08:19:46.568Z\",\n  \"agent_id\": \"cristiancardarello\",\n  \"session_id\": \"cristiancardarello_1780609871683\",\n  \"trace_id\": \"trace_cristiancardarello_cristiancardarello_1780609871683_1780609871684\",\n  \"title\": \"Suite 5.3.36 fast path locale\",\n  \"phase\": \"during\",\n  \"status\": \"in_progress\",\n  \"summary\": \"Checklist Suite creata; runtime live 5.3.35 OK; performance probe ha trovato colli su enterprise-core/snapshot, completion-map, ai-control-tower-score; patch locale 5.3.36 aggiunge fast path read-only default e full detail solo admin full/refresh; test locali OK.\",\n  \"files\": [],\n  \"tests\": [],\n  \"next\": \"\",\n  \"task_contract_id\": \"2026-06-04t21_51_11.685z_cristiancardarello_traduzione_pagina_suite_governance_f\",\n  \"latest_core_report\": \"/Users/cristiancardarello/skinharmony-codex/reports/codex-core/codex_core_gate_latest.json\"\n}","redactions":0}
