{
  "checkpoint_id": "2026-05-24t16_31_11.377z_cristiancardarello_during_suite_5.2.33",
  "generated_at": "2026-05-24T16:31:11.378Z",
  "agent_id": "cristiancardarello",
  "session_id": "cristiancardarello_1779639922426",
  "title": "During Suite 5.2.33",
  "phase": "during",
  "status": "in_progress",
  "summary": "Implementata modifica locale: versione 5.2.33, anteprima modificabile primaria, link esterno per verifica WordPress, test in corso e closure package completata.",
  "files": [],
  "tests": [],
  "next": "",
  "latest_core_report": "/Users/cristiancardarello/skinharmony-codex/reports/codex-core/codex_core_gate_latest.json"
}